_rl_renderPM.cpython-311-aarch64-linux-gnu.so
rl_renderPM.libs/libpng15-7864b8f1.so.15.13.0
rl_renderPM.libs/libbz2-738ca772.so.1.0.6
rl_renderPM.libs/libfreetype-eea08430.so.6.14.0
rl_renderPM-4.0.3.dist-info/top_level.txt
rl_renderPM-4.0.3.dist-info/WHEEL
rl_renderPM-4.0.3.dist-info/RECORD
rl_renderPM-4.0.3.dist-info/METADATA
