Metadata-Version: 2.1
Name: rl_renderPM
Version: 4.0.3
Summary: Bitmap Render Acclerator for ReportLab
Home-page: http://www.reportlab.com/
Author: Andy Robinson, Robin Becker, the ReportLab team and the community
Author-email: reportlab-users@lists2.reportlab.com
License: BSD license (see LICENSE.txt for details), Copyright (c) 2000-2022, ReportLab Inc.
Classifier: Development Status :: 5 - Production/Stable
Classifier: Intended Audience :: Developers
Classifier: License :: OSI Approved :: BSD License
Classifier: Topic :: Printing
Classifier: Topic :: Text Processing :: Markup
Classifier: Programming Language :: Python :: 3
Classifier: Programming Language :: Python :: 3.7
Classifier: Programming Language :: Python :: 3.8
Classifier: Programming Language :: Python :: 3.9
Classifier: Programming Language :: Python :: 3.10
Classifier: Programming Language :: Python :: 3.11
Requires-Python: >=3.7,<4
